Metadata-Version: 1.1
Name: ismscode
Version: 0.0.2
Summary: VIRTUAL NUMBER AND RECEIVER SMS
Home-page: UNKNOWN
Author: Phansivang
Author-email: Phansivang@gmail.com
License: MIT
Keywords: Virtual number
Platform: UNKNOWN
Classifier: Development Status :: 5 - Production/Stable
Classifier: Intended Audience :: Education
Classifier: Operating System :: Microsoft :: Windows :: Windows 10
Classifier: License :: OSI Approved :: MIT License
Classifier: Programming Language :: Python :: 3
